<annotation>
	<folder>M02-20191203-11h19</folder>
	<filename>M02-20191203-11h19-126.jpg</filename>
	<path>/home/mina/PythonLibs/data-trainning/source_images/M02-20191203-11h19/M02-20191203-11h19-126.jpg</path>
	<source>
		<database>Unknown</database>
	</source>
	<size>
		<width>1280</width>
		<height>720</height>
		<depth>3</depth>
	</size>
	<segmented>0</segmented>
	<object>
		<name>parcel</name>
		<pose>Unspecified</pose>
		<truncated>0</truncated>
		<difficult>0</difficult>
		<bndbox>
			<xmin>750</xmin>
			<ymin>136</ymin>
			<xmax>777</xmax>
			<ymax>160</ymax>
		</bndbox>
	</object>
	<object>
		<name>parcel</name>
		<pose>Unspecified</pose>
		<truncated>0</truncated>
		<difficult>0</difficult>
		<bndbox>
			<xmin>744</xmin>
			<ymin>163</ymin>
			<xmax>787</xmax>
			<ymax>193</ymax>
		</bndbox>
	</object>
	<object>
		<name>parcel</name>
		<pose>Unspecified</pose>
		<truncated>0</truncated>
		<difficult>0</difficult>
		<bndbox>
			<xmin>752</xmin>
			<ymin>211</ymin>
			<xmax>789</xmax>
			<ymax>235</ymax>
		</bndbox>
	</object>
	<object>
		<name>parcel</name>
		<pose>Unspecified</pose>
		<truncated>0</truncated>
		<difficult>0</difficult>
		<bndbox>
			<xmin>768</xmin>
			<ymin>360</ymin>
			<xmax>806</xmax>
			<ymax>408</ymax>
		</bndbox>
	</object>
	<object>
		<name>parcel</name>
		<pose>Unspecified</pose>
		<truncated>0</truncated>
		<difficult>0</difficult>
		<bndbox>
			<xmin>760</xmin>
			<ymin>521</ymin>
			<xmax>814</xmax>
			<ymax>578</ymax>
		</bndbox>
	</object>
	<object>
		<name>parcel</name>
		<pose>Unspecified</pose>
		<truncated>1</truncated>
		<difficult>0</difficult>
		<bndbox>
			<xmin>761</xmin>
			<ymin>654</ymin>
			<xmax>845</xmax>
			<ymax>720</ymax>
		</bndbox>
	</object>
	<object>
		<name>parcel</name>
		<pose>Unspecified</pose>
		<truncated>0</truncated>
		<difficult>0</difficult>
		<bndbox>
			<xmin>1079</xmin>
			<ymin>568</ymin>
			<xmax>1121</xmax>
			<ymax>603</ymax>
		</bndbox>
	</object>
</annotation>
